{
  "ProcessInfo": [
    {
      "cpu_percent": "0.00684722154375207",
      "create_time": "1525584315000",
      "exe": "",
      "memory_percent": "0.107260525",
      "name": "systemd",
      "pid": "1",
      "status": "Sleep",
      "username": "root"
    },
    {
      "cpu_percent": "0",
      "create_time": "1525584315000",
      "exe": "",
      "memory_percent": "0",
      "name": "kthreadd",
      "pid": "2",
      "status": "Sleep",
      "username": "root"
    },
    {
      "cpu_percent": "0",
      "create_time": "1525584315000",
      "exe": "",
      "memory_percent": "0",
      "name": "kworker/0:0H",
      "pid": "4",
      "status": "Idle",
      "username": "root"
    },
    {
      "cpu_percent": "0",
      "create_time": "1525584315000",
      "exe": "",
      "memory_percent": "0",
      "name": "mm_percpu_wq",
      "pid": "6",
      "status": "Idle",
      "username": "root"
    },
    {
      "cpu_percent": "0.009212623993591696",
      "create_time": "1525584315000",
      "exe": "",
      "memory_percent": "0",
      "name": "ksoftirqd/0",
      "pid": "7",
      "status": "Sleep",
      "username": "root"
    },
    {
      "cpu_percent": "0.02365403386301507",
      "create_time": "1525584315000",
      "exe": "",
      "memory_percent": "0",
      "name": "rcu_preempt",
      "pid": "8",
      "status": "Idle",
      "username": "root"
    },
    {
      "cpu_percent": "0.0004979796425114846",
      "create_time": "1525584315000",
      "exe": "",
      "memory_percent": "0",
      "name": "rcu_sched",
      "pid": "9",
      "status": "Idle",
      "username": "root"
    },
    {
      "cpu_percent": "0",
      "create_time": "1525584315000",
      "exe": "",
      "memory_percent": "0",
      "name": "rcu_bh",
      "pid": "10",
      "status": "Idle",
      "username": "root"
    },
    {
      "cpu_percent": "0.009337117754090869",
      "create_time": "1525584315000",
      "exe": "",
      "memory_percent": "0",
      "name": "rcuc/0",
      "pid": "11",
      "status": "Sleep",
      "username": "root"
    },
    {
      "cpu_percent": "0",
      "create_time": "1525584315000",
      "exe": "",
      "memory_percent": "0",
      "name": "rcub/0",
      "pid": "12",
      "status": "Sleep",
      "username": "root"
    },
    {
      "cpu_percent": "0",
      "create_time": "1525584315000",
      "exe": "",
      "memory_percent": "0",
      "name": "migration/0",
      "pid": "13",
      "status": "Sleep",
      "username": "root"
    },
    {
      "cpu_percent": "0.0001244948925451951",
      "create_time": "1525584315000",
      "exe": "",
      "memory_percent": "0",
      "name": "watchdog/0",
      "pid": "14",
      "status": "Sleep",
      "username": "root"
    },
    {
      "cpu_percent": "0",
      "create_time": "1525584315000",
      "exe": "",
      "memory_percent": "0",
      "name": "cpuhp/0",
      "pid": "15",
      "status": "Sleep",
      "username": "root"
    },
    {
      "cpu_percent": "0",
      "create_time": "1525584315000",
      "exe": "",
      "memory_percent": "0",
      "name": "cpuhp/1",
      "pid": "16",
      "status": "Sleep",
      "username": "root"
    },
    {
      "cpu_percent": "0.00012449488194516577",
      "create_time": "1525584315000",
      "exe": "",
      "memory_percent": "0",
      "name": "watchdog/1",
      "pid": "17",
      "status": "Sleep",
      "username": "root"
    },
    {
      "cpu_percent": "0",
      "create_time": "1525584315000",
      "exe": "",
      "memory_percent": "0",
      "name": "migration/1",
      "pid": "18",
      "status": "Sleep",
      "username": "root"
    },
    {
      "cpu_percent": "0.008590146349133555",
      "create_time": "1525584315000",
      "exe": "",
      "memory_percent": "0",
      "name": "rcuc/1",
      "pid": "19",
      "status": "Sleep",
      "username": "root"
    },
    {
      "cpu_percent": "0.005975753826919753",
      "create_time": "1525584315000",
      "exe": "",
      "memory_percent": "0",
      "name": "ksoftirqd/1",
      "pid": "20",
      "status": "Sleep",
      "username": "root"
    },
    {
      "cpu_percent": "0",
      "create_time": "1525584315000",
      "exe": "",
      "memory_percent": "0",
      "name": "kworker/1:0H",
      "pid": "22",
      "status": "Idle",
      "username": "root"
    },
    {
      "cpu_percent": "0",
      "create_time": "1525584315000",
      "exe": "",
      "memory_percent": "0",
      "name": "cpuhp/2",
      "pid": "23",
      "status": "Sleep",
      "username": "root"
    },
    {
      "cpu_percent": "0.0001244948613402885",
      "create_time": "1525584315000",
      "exe": "",
      "memory_percent": "0",
      "name": "watchdog/2",
      "pid": "24",
      "status": "Sleep",
      "username": "root"
    },
    {
      "cpu_percent": "0",
      "create_time": "1525584315000",
      "exe": "",
      "memory_percent": "0",
      "name": "migration/2",
      "pid": "25",
      "status": "Sleep",
      "username": "root"
    },
    {
      "cpu_percent": "0.008963629273958178",
      "create_time": "1525584315000",
      "exe": "",
      "memory_percent": "0",
      "name": "rcuc/2",
      "pid": "26",
      "status": "Sleep",
      "username": "root"
    },
    {
      "cpu_percent": "0.005104288650377449",
      "create_time": "1525584315000",
      "exe": "",
      "memory_percent": "0",
      "name": "ksoftirqd/2",
      "pid": "27",
      "status": "Sleep",
      "username": "root"
    },
    {
      "cpu_percent": "0",
      "create_time": "1525584315000",
      "exe": "",
      "memory_percent": "0",
      "name": "kworker/2:0H",
      "pid": "29",
      "status": "Idle",
      "username": "root"
    },
    {
      "cpu_percent": "0",
      "create_time": "1525584315000",
      "exe": "",
      "memory_percent": "0",
      "name": "cpuhp/3",
      "pid": "30",
      "status": "Sleep",
      "username": "root"
    },
    {
      "cpu_percent": "0.00012449481328666347",
      "create_time": "1525584315000",
      "exe": "",
      "memory_percent": "0",
      "name": "watchdog/3",
      "pid": "31",
      "status": "Sleep",
      "username": "root"
    },
    {
      "cpu_percent": "0",
      "create_time": "1525584315000",
      "exe": "",
      "memory_percent": "0",
      "name": "migration/3",
      "pid": "32",
      "status": "Sleep",
      "username": "root"
    },
    {
      "cpu_percent": "0.01531286058030421",
      "create_time": "1525584315000",
      "exe": "",
      "memory_percent": "0",
      "name": "rcuc/3",
      "pid": "33",
      "status": "Sleep",
      "username": "root"
    },
    {
      "cpu_percent": "0.010457562872167816",
      "create_time": "1525584315000",
      "exe": "",
      "memory_percent": "0",
      "name": "ksoftirqd/3",
      "pid": "34",
      "status": "Sleep",
      "username": "root"
    },
    {
      "cpu_percent": "0",
      "create_time": "1525584315000",
      "exe": "",
      "memory_percent": "0",
      "name": "kworker/3:0H",
      "pid": "36",
      "status": "Idle",
      "username": "root"
    },
    {
      "cpu_percent": "0",
      "create_time": "1525584315000",
      "exe": "",
      "memory_percent": "0",
      "name": "kdevtmpfs",
      "pid": "37",
      "status": "Sleep",
      "username": "root"
    },
    {
      "cpu_percent": "0",
      "create_time": "1525584315000",
      "exe": "",
      "memory_percent": "0",
      "name": "netns",
      "pid": "38",
      "status": "Idle",
      "username": "root"
    },
    {
      "cpu_percent": "0",
      "create_time": "1525584315000",
      "exe": "",
      "memory_percent": "0",
      "name": "rcu_tasks_kthre",
      "pid": "39",
      "status": "Sleep",
      "username": "root"
    },
    {
      "cpu_percent": "0",
      "create_time": "1525584315000",
      "exe": "",
      "memory_percent": "0",
      "name": "khungtaskd",
      "pid": "42",
      "status": "Sleep",
      "username": "root"
    },
    {
      "cpu_percent": "0",
      "create_time": "1525584315000",
      "exe": "",
      "memory_percent": "0",
      "name": "oom_reaper",
      "pid": "43",
      "status": "Sleep",
      "username": "root"
    },
    {
      "cpu_percent": "0",
      "create_time": "1525584315000",
      "exe": "",
      "memory_percent": "0",
      "name": "writeback",
      "pid": "44",
      "status": "Idle",
      "username": "root"
    },
    {
      "cpu_percent": "0",
      "create_time": "1525584315000",
      "exe": "",
      "memory_percent": "0",
      "name": "kcompactd0",
      "pid": "45",
      "status": "Sleep",
      "username": "root"
    },
    {
      "cpu_percent": "0",
      "create_time": "1525584315000",
      "exe": "",
      "memory_percent": "0",
      "name": "ksmd",
      "pid": "46",
      "status": "Sleep",
      "username": "root"
    },
    {
      "cpu_percent": "0",
      "create_time": "1525584315000",
      "exe": "",
      "memory_percent": "0",
      "name": "khugepaged",
      "pid": "47",
      "status": "Sleep",
      "username": "root"
    },
    {
      "cpu_percent": "0",
      "create_time": "1525584315000",
      "exe": "",
      "memory_percent": "0",
      "name": "crypto",
      "pid": "48",
      "status": "Idle",
      "username": "root"
    },
    {
      "cpu_percent": "0",
      "create_time": "1525584315000",
      "exe": "",
      "memory_percent": "0",
      "name": "kintegrityd",
      "pid": "49",
      "status": "Idle",
      "username": "root"
    },
    {
      "cpu_percent": "0",
      "create_time": "1525584315000",
      "exe": "",
      "memory_percent": "0",
      "name": "kblockd",
      "pid": "50",
      "status": "Idle",
      "username": "root"
    },
    {
      "cpu_percent": "0",
      "create_time": "1525584315000",
      "exe": "",
      "memory_percent": "0",
      "name": "edac-poller",
      "pid": "53",
      "status": "Idle",
      "username": "root"
    },
    {
      "cpu_percent": "0",
      "create_time": "1525584315000",
      "exe": "",
      "memory_percent": "0",
      "name": "devfreq_wq",
      "pid": "54",
      "status": "Idle",
      "username": "root"
    },
    {
      "cpu_percent": "0",
      "create_time": "1525584315000",
      "exe": "",
      "memory_percent": "0",
      "name": "watchdogd",
      "pid": "55",
      "status": "Sleep",
      "username": "root"
    },
    {
      "cpu_percent": "0",
      "create_time": "1525584315000",
      "exe": "",
      "memory_percent": "0",
      "name": "kswapd0",
      "pid": "58",
      "status": "Sleep",
      "username": "root"
    },
    {
      "cpu_percent": "0",
      "create_time": "1525584315000",
      "exe": "",
      "memory_percent": "0",
      "name": "kthrotld",
      "pid": "97",
      "status": "Idle",
      "username": "root"
    },
    {
      "cpu_percent": "0",
      "create_time": "1525584315000",
      "exe": "",
      "memory_percent": "0",
      "name": "acpi_thermal_pm",
      "pid": "98",
      "status": "Idle",
      "username": "root"
    },
    {
      "cpu_percent": "0",
      "create_time": "1525584315000",
      "exe": "",
      "memory_percent": "0",
      "name": "nvme-wq",
      "pid": "99",
      "status": "Idle",
      "username": "root"
    },
    {
      "cpu_percent": "0",
      "create_time": "1525584315000",
      "exe": "",
      "memory_percent": "0",
      "name": "nvme-reset-wq",
      "pid": "100",
      "status": "Idle",
      "username": "root"
    },
    {
      "cpu_percent": "0",
      "create_time": "1525584315000",
      "exe": "",
      "memory_percent": "0",
      "name": "nvme-delete-wq",
      "pid": "101",
      "status": "Idle",
      "username": "root"
    },
    {
      "cpu_percent": "0",
      "create_time": "1525584315000",
      "exe": "",
      "memory_percent": "0",
      "name": "ipv6_addrconf",
      "pid": "102",
      "status": "Idle",
      "username": "root"
    },
    {
      "cpu_percent": "0",
      "create_time": "1525584315000",
      "exe": "",
      "memory_percent": "0",
      "name": "kstrp",
      "pid": "111",
      "status": "Idle",
      "username": "root"
    },
    {
      "cpu_percent": "0",
      "create_time": "1525584315000",
      "exe": "",
      "memory_percent": "0",
      "name": "charger_manager",
      "pid": "120",
      "status": "Idle",
      "username": "root"
    },
    {
      "cpu_percent": "0",
      "create_time": "1525584315000",
      "exe": "",
      "memory_percent": "0",
      "name": "ata_sff",
      "pid": "158",
      "status": "Idle",
      "username": "root"
    },
    {
      "cpu_percent": "0",
      "create_time": "1525584315000",
      "exe": "",
      "memory_percent": "0",
      "name": "scsi_eh_0",
      "pid": "161",
      "status": "Sleep",
      "username": "root"
    },
    {
      "cpu_percent": "0",
      "create_time": "1525584315000",
      "exe": "",
      "memory_percent": "0",
      "name": "scsi_tmf_0",
      "pid": "162",
      "status": "Idle",
      "username": "root"
    },
    {
      "cpu_percent": "0",
      "create_time": "1525584315000",
      "exe": "",
      "memory_percent": "0",
      "name": "scsi_eh_1",
      "pid": "163",
      "status": "Sleep",
      "username": "root"
    },
    {
      "cpu_percent": "0",
      "create_time": "1525584315000",
      "exe": "",
      "memory_percent": "0",
      "name": "scsi_tmf_1",
      "pid": "164",
      "status": "Idle",
      "username": "root"
    },
    {
      "cpu_percent": "0",
      "create_time": "1525584315000",
      "exe": "",
      "memory_percent": "0",
      "name": "scsi_eh_2",
      "pid": "165",
      "status": "Sleep",
      "username": "root"
    },
    {
      "cpu_percent": "0",
      "create_time": "1525584315000",
      "exe": "",
      "memory_percent": "0",
      "name": "scsi_tmf_2",
      "pid": "166",
      "status": "Idle",
      "username": "root"
    },
    {
      "cpu_percent": "0",
      "create_time": "1525584315000",
      "exe": "",
      "memory_percent": "0",
      "name": "scsi_eh_3",
      "pid": "167",
      "status": "Sleep",
      "username": "root"
    },
    {
      "cpu_percent": "0",
      "create_time": "1525584315000",
      "exe": "",
      "memory_percent": "0",
      "name": "scsi_tmf_3",
      "pid": "168",
      "status": "Idle",
      "username": "root"
    },
    {
      "cpu_percent": "0.00024902018888846636",
      "create_time": "1525584316000",
      "exe": "",
      "memory_percent": "0",
      "name": "kworker/0:1H",
      "pid": "173",
      "status": "Idle",
      "username": "root"
    },
    {
      "cpu_percent": "0.0009960807158703889",
      "create_time": "1525584316000",
      "exe": "",
      "memory_percent": "0",
      "name": "jbd2/sda5-8",
      "pid": "185",
      "status": "Sleep",
      "username": "root"
    },
    {
      "cpu_percent": "0",
      "create_time": "1525584316000",
      "exe": "",
      "memory_percent": "0",
      "name": "ext4-rsv-conver",
      "pid": "186",
      "status": "Idle",
      "username": "root"
    },
    {
      "cpu_percent": "0.0070970743756408085",
      "create_time": "1525584316000",
      "exe": "",
      "memory_percent": "0.36027646",
      "name": "systemd-journald",
      "pid": "210",
      "status": "Sleep",
      "username": "root"
    },
    {
      "cpu_percent": "0",
      "create_time": "1525584316000",
      "exe": "",
      "memory_percent": "0.01887587",
      "name": "lvmetad",
      "pid": "219",
      "status": "Sleep",
      "username": "root"
    },
    {
      "cpu_percent": "0.0031127516094731204",
      "create_time": "1525584316000",
      "exe": "",
      "memory_percent": "0.101513535",
      "name": "systemd-udevd",
      "pid": "227",
      "status": "Sleep",
      "username": "root"
    },
    {
      "cpu_percent": "0",
      "create_time": "1525584316000",
      "exe": "",
      "memory_percent": "0",
      "name": "kworker/1:1H",
      "pid": "229",
      "status": "Idle",
      "username": "root"
    },
    {
      "cpu_percent": "0",
      "create_time": "1525584316000",
      "exe": "",
      "memory_percent": "0",
      "name": "irq/39-DLL0665:",
      "pid": "246",
      "status": "Sleep",
      "username": "root"
    },
    {
      "cpu_percent": "0",
      "create_time": "1525584316000",
      "exe": "",
      "memory_percent": "0",
      "name": "irq/47-mei_me",
      "pid": "247",
      "status": "Sleep",
      "username": "root"
    },
    {
      "cpu_percent": "0",
      "create_time": "1525584316000",
      "exe": "",
      "memory_percent": "0",
      "name": "kmemstick",
      "pid": "251",
      "status": "Idle",
      "username": "root"
    },
    {
      "cpu_percent": "0",
      "create_time": "1525584316000",
      "exe": "",
      "memory_percent": "0",
      "name": "cfg80211",
      "pid": "291",
      "status": "Idle",
      "username": "root"
    },
    {
      "cpu_percent": "0.005602951558309338",
      "create_time": "1525584316000",
      "exe": "",
      "memory_percent": "0",
      "name": "jbd2/sda6-8",
      "pid": "322",
      "status": "Sleep",
      "username": "root"
    },
    {
      "cpu_percent": "0",
      "create_time": "1525584316000",
      "exe": "",
      "memory_percent": "0",
      "name": "ext4-rsv-conver",
      "pid": "325",
      "status": "Idle",
      "username": "root"
    },
    {
      "cpu_percent": "0",
      "create_time": "1525584316000",
      "exe": "",
      "memory_percent": "0",
      "name": "kworker/u9:0",
      "pid": "331",
      "status": "Idle",
      "username": "root"
    },
    {
      "cpu_percent": "0",
      "create_time": "1525584316000",
      "exe": "",
      "memory_percent": "0",
      "name": "wl_event_handle",
      "pid": "333",
      "status": "Sleep",
      "username": "root"
    },
    {
      "cpu_percent": "0.023532392087660624",
      "create_time": "1525584316000",
      "exe": "",
      "memory_percent": "0",
      "name": "i915/signal:0",
      "pid": "334",
      "status": "Sleep",
      "username": "root"
    },
    {
      "cpu_percent": "0.0006225500310980135",
      "create_time": "1525584316000",
      "exe": "",
      "memory_percent": "0",
      "name": "i915/signal:1",
      "pid": "335",
      "status": "Sleep",
      "username": "root"
    },
    {
      "cpu_percent": "0.00037353000226800817",
      "create_time": "1525584316000",
      "exe": "",
      "memory_percent": "0",
      "name": "i915/signal:2",
      "pid": "337",
      "status": "Sleep",
      "username": "root"
    },
    {
      "cpu_percent": "0.0003735299872958498",
      "create_time": "1525584316000",
      "exe": "",
      "memory_percent": "0",
      "name": "i915/signal:4",
      "pid": "339",
      "status": "Sleep",
      "username": "root"
    },
    {
      "cpu_percent": "0.0006225494709384962",
      "create_time": "1525584316000",
      "exe": "",
      "memory_percent": "0.050632913",
      "name": "systemd-timesyncd",
      "pid": "349",
      "status": "Sleep",
      "username": "systemd-timesync"
    },
    {
      "cpu_percent": "0",
      "create_time": "1525584317000",
      "exe": "",
      "memory_percent": "0",
      "name": "kworker/2:1H",
      "pid": "378",
      "status": "Idle",
      "username": "root"
    },
    {
      "cpu_percent": "0",
      "create_time": "1525584317000",
      "exe": "",
      "memory_percent": "0",
      "name": "kworker/u9:1",
      "pid": "499",
      "status": "Idle",
      "username": "root"
    },
    {
      "cpu_percent": "0.019552919447598942",
      "create_time": "1525584318000",
      "exe": "",
      "memory_percent": "0.05979836",
      "name": "dbus-daemon",
      "pid": "591",
      "status": "Sleep",
      "username": "dbus"
    },
    {
      "cpu_percent": "0.009589647917970656",
      "create_time": "1525584318000",
      "exe": "",
      "memory_percent": "0.41457555",
      "name": "firewalld",
      "pid": "592",
      "status": "Sleep",
      "username": "root"
    },
    {
      "cpu_percent": "0.0022417357656833344",
      "create_time": "1525584318000",
      "exe": "",
      "memory_percent": "0.076048456",
      "name": "systemd-logind",
      "pid": "593",
      "status": "Sleep",
      "username": "root"
    },
    {
      "cpu_percent": "0.000124540864899576",
      "create_time": "1525584318000",
      "exe": "",
      "memory_percent": "0.062374596",
      "name": "bluetoothd",
      "pid": "594",
      "status": "Sleep",
      "username": "root"
    },
    {
      "cpu_percent": "0.024160926298235085",
      "create_time": "1525584318000",
      "exe": "",
      "memory_percent": "0.21897991",
      "name": "NetworkManager",
      "pid": "658",
      "status": "Sleep",
      "username": "root"
    },
    {
      "cpu_percent": "0.0024908169851018866",
      "create_time": "1525584318000",
      "exe": "",
      "memory_percent": "0.04171518",
      "name": "ss-local",
      "pid": "682",
      "status": "Sleep",
      "username": "nobody"
    },
    {
      "cpu_percent": "0.0002490816854383149",
      "create_time": "1525584318000",
      "exe": "",
      "memory_percent": "0.18162452",
      "name": "sddm",
      "pid": "685",
      "status": "Sleep",
      "username": "root"
    },
    {
      "cpu_percent": "4.771159479499161",
      "create_time": "1525584318000",
      "exe": "",
      "memory_percent": "0.8735911",
      "name": "Xorg",
      "pid": "722",
      "status": "Running",
      "username": "root"
    },
    {
      "cpu_percent": "0.003985802989118026",
      "create_time": "1525584319000",
      "exe": "",
      "memory_percent": "0.26292452",
      "name": "polkitd",
      "pid": "826",
      "status": "Sleep",
      "username": "polkitd"
    },
    {
      "cpu_percent": "0.001743788720450605",
      "create_time": "1525584319000",
      "exe": "",
      "memory_percent": "0.08224133",
      "name": "wpa_supplicant",
      "pid": "830",
      "status": "Sleep",
      "username": "root"
    },
    {
      "cpu_percent": "0.07161988871887227",
      "create_time": "1525584319000",
      "exe": "",
      "memory_percent": "1.0345563",
      "name": "mysqld",
      "pid": "905",
      "status": "Sleep",
      "username": "mysql"
    },
    {
      "cpu_percent": "0",
      "create_time": "1525584319000",
      "exe": "",
      "memory_percent": "0",
      "name": "kworker/3:1H",
      "pid": "972",
      "status": "Idle",
      "username": "root"
    },
    {
      "cpu_percent": "0.016318909397477595",
      "create_time": "1525584320000",
      "exe": "",
      "memory_percent": "0.13817534",
      "name": "udisksd",
      "pid": "1582",
      "status": "Sleep",
      "username": "root"
    },
    {
      "cpu_percent": "0.008346312035793935",
      "create_time": "1525584320000",
      "exe": "",
      "memory_percent": "0.10587332",
      "name": "upowerd",
      "pid": "1621",
      "status": "Sleep",
      "username": "root"
    },
    {
      "cpu_percent": "0.0009970712978571237",
      "create_time": "1525584324000",
      "exe": "",
      "memory_percent": "0.1841512",
      "name": "sddm-helper",
      "pid": "3165",
      "status": "Sleep",
      "username": "root"
    },
    {
      "cpu_percent": "0.00024926781393563017",
      "create_time": "1525584324000",
      "exe": "/usr/lib/systemd/systemd",
      "memory_percent": "0.097896904",
      "name": "systemd",
      "pid": "3210",
      "status": "Sleep",
      "username": "zhang"
    },
    {
      "cpu_percent": "0",
      "create_time": "1525584324000",
      "exe": "",
      "memory_percent": "0.029676236",
      "name": "(sd-pam)",
      "pid": "3212",
      "status": "Sleep",
      "username": "zhang"
    },
    {
      "cpu_percent": "0.03614833539052938",
      "create_time": "1525584325000",
      "exe": "/usr/bin/kwalletd5",
      "memory_percent": "0.49884814",
      "name": "kwalletd5",
      "pid": "3231",
      "status": "Sleep",
      "username": "zhang"
    },
    {
      "cpu_percent": "0.00012464942745079802",
      "create_time": "1525584325000",
      "exe": "/usr/bin/bash",
      "memory_percent": "0.038494885",
      "name": "startkde",
      "pid": "3235",
      "status": "Sleep",
      "username": "zhang"
    },
    {
      "cpu_percent": "0.012340292976117058",
      "create_time": "1525584325000",
      "exe": "/usr/bin/dbus-daemon",
      "memory_percent": "0.051029254",
      "name": "dbus-daemon",
      "pid": "3259",
      "status": "Sleep",
      "username": "zhang"
    },
    {
      "cpu_percent": "0",
      "create_time": "1525584325000",
      "exe": "/usr/lib/kf5/start_kdeinit",
      "memory_percent": "0.0009908593",
      "name": "start_kdeinit",
      "pid": "3405",
      "status": "Sleep",
      "username": "zhang"
    },
    {
      "cpu_percent": "0.0009971953337674093",
      "create_time": "1525584325000",
      "exe": "/usr/bin/kdeinit5",
      "memory_percent": "0.26594666",
      "name": "kdeinit5",
      "pid": "3411",
      "status": "Sleep",
      "username": "zhang"
    },
    {
      "cpu_percent": "0.032907444701476475",
      "create_time": "1525584325000",
      "exe": "/usr/lib/kf5/klauncher",
      "memory_percent": "0.4742748",
      "name": "klauncher",
      "pid": "3431",
      "status": "Sleep",
      "username": "zhang"
    },
    {
      "cpu_percent": "0.07279525343990044",
      "create_time": "1525584325000",
      "exe": "/usr/bin/kdeinit5",
      "memory_percent": "0.694741",
      "name": "kded5",
      "pid": "3471",
      "status": "Sleep",
      "username": "zhang"
    },
    {
      "cpu_percent": "0.03265814306351436",
      "create_time": "1525584325000",
      "exe": "/usr/bin/kaccess",
      "memory_percent": "0.48616514",
      "name": "kaccess",
      "pid": "3509",
      "status": "Sleep",
      "username": "zhang"
    },
    {
      "cpu_percent": "0.03465253188911099",
      "create_time": "1525584325000",
      "exe": "/usr/bin/kactivitymanagerd",
      "memory_percent": "0.35517353",
      "name": "kactivitymanagerd",
      "pid": "3544",
      "status": "Sleep",
      "username": "zhang"
    },
    {
      "cpu_percent": "0.03141164626149128",
      "create_time": "1525584325000",
      "exe": "/usr/bin/kglobalaccel5",
      "memory_percent": "0.46862692",
      "name": "kglobalaccel5",
      "pid": "3563",
      "status": "Sleep",
      "username": "zhang"
    },
    {
      "cpu_percent": "0",
      "create_time": "1525584325000",
      "exe": "/usr/lib/dconf-service",
      "memory_percent": "0.058559787",
      "name": "dconf-service",
      "pid": "3576",
      "status": "Sleep",
      "username": "zhang"
    },
    {
      "cpu_percent": "0",
      "create_time": "1525584325000",
      "exe": "/usr/bin/kwrapper5",
      "memory_percent": "0.09338849",
      "name": "kwrapper5",
      "pid": "3583",
      "status": "Sleep",
      "username": "zhang"
    },
    {
      "cpu_percent": "0.04263008624632348",
      "create_time": "1525584325000",
      "exe": "/usr/bin/ksmserver",
      "memory_percent": "0.5444772",
      "name": "ksmserver",
      "pid": "3588",
      "status": "Sleep",
      "username": "zhang"
    },
    {
      "cpu_percent": "0.027924939546918978",
      "create_time": "1525584326000",
      "exe": "/usr/lib/kf5/kscreen_backend_launcher",
      "memory_percent": "0.23324828",
      "name": "kscreen_backend_launcher",
      "pid": "3645",
      "status": "Sleep",
      "username": "zhang"
    },
    {
      "cpu_percent": "3.523593970156223",
      "create_time": "1525584327000",
      "exe": "/usr/bin/kwin_x11",
      "memory_percent": "1.56531",
      "name": "kwin_x11",
      "pid": "4099",
      "status": "Sleep",
      "username": "zhang"
    },
    {
      "cpu_percent": "0.03054670687801725",
      "create_time": "1525584327000",
      "exe": "/usr/bin/baloo_file",
      "memory_percent": "3.5321162",
      "name": "baloo_file",
      "pid": "4109",
      "status": "Sleep",
      "username": "zhang"
    },
    {
      "cpu_percent": "0.043264109395588585",
      "create_time": "1525584327000",
      "exe": "/usr/bin/krunner",
      "memory_percent": "0.85981816",
      "name": "krunner",
      "pid": "4112",
      "status": "Sleep",
      "username": "zhang"
    },
    {
      "cpu_percent": "1.258150167524037",
      "create_time": "1525584327000",
      "exe": "/usr/bin/plasmashell",
      "memory_percent": "3.0906885",
      "name": "plasmashell",
      "pid": "4118",
      "status": "Sleep",
      "username": "zhang"
    },
    {
      "cpu_percent": "0.031668826550866176",
      "create_time": "1525584327000",
      "exe": "",
      "memory_percent": "0.5199534",
      "name": "polkit-kde-authentication-agent-1",
      "pid": "4132",
      "status": "Sleep",
      "username": "zhang"
    },
    {
      "cpu_percent": "0.030047979809727125",
      "create_time": "1525584327000",
      "exe": "/usr/bin/xembedsniproxy",
      "memory_percent": "0.2634695",
      "name": "xembedsniproxy",
      "pid": "4135",
      "status": "Sleep",
      "username": "zhang"
    },
    {
      "cpu_percent": "0.004363814317459792",
      "create_time": "1525584327000",
      "exe": "/usr/bin/pulseaudio",
      "memory_percent": "0.1549704",
      "name": "pulseaudio",
      "pid": "4151",
      "status": "Sleep",
      "username": "zhang"
    },
    {
      "cpu_percent": "0.0007480824170298987",
      "create_time": "1525584327000",
      "exe": "",
      "memory_percent": "0.03388739",
      "name": "rtkit-daemon",
      "pid": "4155",
      "status": "Sleep",
      "username": "rtkit"
    },
    {
      "cpu_percent": "0.036406675797071804",
      "create_time": "1525584327000",
      "exe": "/usr/lib/org_kde_powerdevil",
      "memory_percent": "0.47625652",
      "name": "org_kde_powerdevil",
      "pid": "4156",
      "status": "Sleep",
      "username": "zhang"
    },
    {
      "cpu_percent": "0",
      "create_time": "1525584327000",
      "exe": "/usr/lib/pulse/gconf-helper",
      "memory_percent": "0.045827243",
      "name": "gconf-helper",
      "pid": "4219",
      "status": "Sleep",
      "username": "zhang"
    },
    {
      "cpu_percent": "0.00012468038592314823",
      "create_time": "1525584327000",
      "exe": "/usr/lib/gconfd-2",
      "memory_percent": "0.07119324",
      "name": "gconfd-2",
      "pid": "4226",
      "status": "Sleep",
      "username": "zhang"
    },
    {
      "cpu_percent": "0.00012469592722485508",
      "create_time": "1525584328000",
      "exe": "/usr/lib/bluetooth/obexd",
      "memory_percent": "0.085065275",
      "name": "obexd",
      "pid": "4242",
      "status": "Sleep",
      "username": "zhang"
    },
    {
      "cpu_percent": "0",
      "create_time": "1525584328000",
      "exe": "",
      "memory_percent": "0",
      "name": "krfcommd",
      "pid": "4247",
      "status": "Sleep",
      "username": "root"
    },
    {
      "cpu_percent": "0.12020686412525936",
      "create_time": "1525584328000",
      "exe": "/usr/bin/ksysguardd",
      "memory_percent": "0.026257772",
      "name": "ksysguardd",
      "pid": "4251",
      "status": "Sleep",
      "username": "zhang"
    },
    {
      "cpu_percent": "0.03342267216387961",
      "create_time": "1525584329000",
      "exe": "/usr/bin/kuiserver5",
      "memory_percent": "0.48571923",
      "name": "kuiserver5",
      "pid": "4260",
      "status": "Sleep",
      "username": "zhang"
    },
    {
      "cpu_percent": "0.09652666859629168",
      "create_time": "1525584329000",
      "exe": "/usr/bin/fcitx",
      "memory_percent": "0.6167604",
      "name": "fcitx",
      "pid": "4270",
      "status": "Sleep",
      "username": "zhang"
    },
    {
      "cpu_percent": "0.014341817096278894",
      "create_time": "1525584329000",
      "exe": "/usr/bin/dbus-daemon",
      "memory_percent": "0.044241868",
      "name": "dbus-daemon",
      "pid": "4275",
      "status": "Sleep",
      "username": "zhang"
    },
    {
      "cpu_percent": "0",
      "create_time": "1525584329000",
      "exe": "/usr/bin/fcitx-dbus-watcher",
      "memory_percent": "0.0025762343",
      "name": "fcitx-dbus-watcher",
      "pid": "4279",
      "status": "Sleep",
      "username": "zhang"
    },
    {
      "cpu_percent": "0.3340168884907542",
      "create_time": "1525584794000",
      "exe": "/tmp/.mount_jetbran9H4wG/usr/share/jetbrains-toolbox/jetbrains-toolbox",
      "memory_percent": "2.977334",
      "name": "jetbrains-toolbox",
      "pid": "5337",
      "status": "Sleep",
      "username": "zhang"
    },
    {
      "cpu_percent": "0.018931594621036843",
      "create_time": "1525584794000",
      "exe": "/home/zhang/.local/share/JetBrains/Toolbox/bin/jetbrains-toolbox",
      "memory_percent": "0.026604572",
      "name": "jetbrains-toolbox",
      "pid": "5347",
      "status": "Sleep",
      "username": "zhang"
    },
    {
      "cpu_percent": "1.409018766365841",
      "create_time": "1525586151000",
      "exe": "/usr/lib/chromium/chromium",
      "memory_percent": "3.309718",
      "name": "chromium",
      "pid": "6287",
      "status": "Sleep",
      "username": "zhang"
    },
    {
      "cpu_percent": "0",
      "create_time": "1525586151000",
      "exe": "",
      "memory_percent": "0.010453566",
      "name": "chrome-sandbox",
      "pid": "6290",
      "status": "Sleep",
      "username": "zhang"
    },
    {
      "cpu_percent": "0.00048414339913677775",
      "create_time": "1525586151000",
      "exe": "/usr/lib/chromium/chromium",
      "memory_percent": "0.9562783",
      "name": "chromium",
      "pid": "6291",
      "status": "Sleep",
      "username": "zhang"
    },
    {
      "cpu_percent": "0.0001613811269067401",
      "create_time": "1525586151000",
      "exe": "",
      "memory_percent": "0.1693874",
      "name": "chromium",
      "pid": "6293",
      "status": "Sleep",
      "username": "zhang"
    },
    {
      "cpu_percent": "0.34073053335708825",
      "create_time": "1525586152000",
      "exe": "/usr/lib/chromium/chromium",
      "memory_percent": "2.1733012",
      "name": "chromium",
      "pid": "6365",
      "status": "Sleep",
      "username": "zhang"
    },
    {
      "cpu_percent": "0",
      "create_time": "1525586152000",
      "exe": "/usr/lib/chromium/chromium",
      "memory_percent": "0.18722287",
      "name": "chromium",
      "pid": "6369",
      "status": "Sleep",
      "username": "zhang"
    },
    {
      "cpu_percent": "1.7732190377502408",
      "create_time": "1525586152000",
      "exe": "",
      "memory_percent": "6.4403872",
      "name": "chromium",
      "pid": "6379",
      "status": "Sleep",
      "username": "zhang"
    },
    {
      "cpu_percent": "0.005649249991517399",
      "create_time": "1525586152000",
      "exe": "",
      "memory_percent": "0.99125564",
      "name": "chromium",
      "pid": "6410",
      "status": "Sleep",
      "username": "zhang"
    },
    {
      "cpu_percent": "0.2817009118847407",
      "create_time": "1525586153000",
      "exe": "",
      "memory_percent": "3.0380242",
      "name": "chromium",
      "pid": "6514",
      "status": "Sleep",
      "username": "zhang"
    },
    {
      "cpu_percent": "0.09669847547426659",
      "create_time": "1525586153000",
      "exe": "",
      "memory_percent": "1.1330972",
      "name": "chromium",
      "pid": "6525",
      "status": "Sleep",
      "username": "zhang"
    },
    {
      "cpu_percent": "0.18564815187712852",
      "create_time": "1525586153000",
      "exe": "",
      "memory_percent": "1.9175605",
      "name": "chromium",
      "pid": "6537",
      "status": "Sleep",
      "username": "zhang"
    },
    {
      "cpu_percent": "0.027941470243205164",
      "create_time": "1525586156000",
      "exe": "",
      "memory_percent": "0.5414551",
      "name": "chromium",
      "pid": "6575",
      "status": "Sleep",
      "username": "zhang"
    },
    {
      "cpu_percent": "0.5079958327736153",
      "create_time": "1525586314000",
      "exe": "",
      "memory_percent": "2.91382",
      "name": "chromium",
      "pid": "7057",
      "status": "Sleep",
      "username": "zhang"
    },
    {
      "cpu_percent": "0.09445804303336147",
      "create_time": "1525587340000",
      "exe": "/usr/bin/dolphin",
      "memory_percent": "0.91867524",
      "name": "dolphin",
      "pid": "7505",
      "status": "Sleep",
      "username": "zhang"
    },
    {
      "cpu_percent": "0.006989495427787851",
      "create_time": "1525587340000",
      "exe": "/usr/bin/kdeinit5",
      "memory_percent": "0.23815304",
      "name": "file.so",
      "pid": "7514",
      "status": "Sleep",
      "username": "zhang"
    },
    {
      "cpu_percent": "0.1264605185800982",
      "create_time": "1525587342000",
      "exe": "/usr/bin/konsole",
      "memory_percent": "0.78342295",
      "name": "konsole",
      "pid": "7553",
      "status": "Sleep",
      "username": "zhang"
    },
    {
      "cpu_percent": "0.0063929485374939615",
      "create_time": "1525587342000",
      "exe": "/usr/bin/zsh",
      "memory_percent": "0.08303401",
      "name": "zsh",
      "pid": "7556",
      "status": "Sleep",
      "username": "zhang"
    },
    {
      "cpu_percent": "0",
      "create_time": "1525587684000",
      "exe": "/usr/bin/bash",
      "memory_percent": "0.044489585",
      "name": "goland.sh",
      "pid": "7947",
      "status": "Sleep",
      "username": "zhang"
    },
    {
      "cpu_percent": "30.032064358019245",
      "create_time": "1525587684000",
      "exe": "/home/zhang/.local/share/JetBrains/Toolbox/apps/Goland/ch-0/181.4668.90/jre64/bin/java",
      "memory_percent": "11.357824",
      "name": "java",
      "pid": "8001",
      "status": "Sleep",
      "username": "zhang"
    },
    {
      "cpu_percent": "0.00686766621786609",
      "create_time": "1525587688000",
      "exe": "/home/zhang/.local/share/JetBrains/Toolbox/apps/Goland/ch-0/181.4668.90/bin/fsnotifier64",
      "memory_percent": "0.025762342",
      "name": "fsnotifier64",
      "pid": "8033",
      "status": "Sleep",
      "username": "zhang"
    },
    {
      "cpu_percent": "0.021863761695291188",
      "create_time": "1525587728000",
      "exe": "",
      "memory_percent": "0",
      "name": "kworker/u8:3",
      "pid": "8074",
      "status": "Idle",
      "username": "root"
    },
    {
      "cpu_percent": "0.4661674981390514",
      "create_time": "1525588793000",
      "exe": "/opt/visual-studio-code/code",
      "memory_percent": "1.4290173",
      "name": "code",
      "pid": "8920",
      "status": "Sleep",
      "username": "zhang"
    },
    {
      "cpu_percent": "0.000562664418636983",
      "create_time": "1525588793000",
      "exe": "/opt/visual-studio-code/code",
      "memory_percent": "0.38925907",
      "name": "code",
      "pid": "8922",
      "status": "Sleep",
      "username": "zhang"
    },
    {
      "cpu_percent": "0.05795443060963589",
      "create_time": "1525588793000",
      "exe": "/opt/visual-studio-code/code",
      "memory_percent": "1.0152345",
      "name": "code",
      "pid": "8950",
      "status": "Sleep",
      "username": "zhang"
    },
    {
      "cpu_percent": "0.42678090199794205",
      "create_time": "1525588793000",
      "exe": "/opt/visual-studio-code/code",
      "memory_percent": "2.39783",
      "name": "code",
      "pid": "8960",
      "status": "Sleep",
      "username": "zhang"
    },
    {
      "cpu_percent": "0.1384154194204343",
      "create_time": "1525588793000",
      "exe": "/opt/visual-studio-code/code",
      "memory_percent": "1.2066189",
      "name": "code",
      "pid": "8966",
      "status": "Sleep",
      "username": "zhang"
    },
    {
      "cpu_percent": "0.033778862502724445",
      "create_time": "1525588795000",
      "exe": "/opt/visual-studio-code/code",
      "memory_percent": "0.8800317",
      "name": "code",
      "pid": "9036",
      "status": "Sleep",
      "username": "zhang"
    },
    {
      "cpu_percent": "0.0344878343716283",
      "create_time": "1525589071000",
      "exe": "",
      "memory_percent": "0",
      "name": "kworker/2:0",
      "pid": "9155",
      "status": "Idle",
      "username": "root"
    },
    {
      "cpu_percent": "0.3132051585763266",
      "create_time": "1525589209000",
      "exe": "",
      "memory_percent": "0.65109366",
      "name": "chromium",
      "pid": "9211",
      "status": "Sleep",
      "username": "zhang"
    },
    {
      "cpu_percent": "0.03094201921086435",
      "create_time": "1525590570000",
      "exe": "",
      "memory_percent": "0",
      "name": "kworker/1:1",
      "pid": "9787",
      "status": "Idle",
      "username": "root"
    },
    {
      "cpu_percent": "0.034769549311459536",
      "create_time": "1525590967000",
      "exe": "",
      "memory_percent": "0",
      "name": "kworker/u8:4",
      "pid": "10116",
      "status": "Idle",
      "username": "root"
    },
    {
      "cpu_percent": "0.031573177326332254",
      "create_time": "1525591334000",
      "exe": "",
      "memory_percent": "0",
      "name": "kworker/0:0",
      "pid": "10437",
      "status": "Idle",
      "username": "root"
    },
    {
      "cpu_percent": "0.020190266168754686",
      "create_time": "1525591456000",
      "exe": "",
      "memory_percent": "0",
      "name": "kworker/3:1",
      "pid": "10499",
      "status": "Idle",
      "username": "root"
    },
    {
      "cpu_percent": "0.01674763928536352",
      "create_time": "1525591631000",
      "exe": "",
      "memory_percent": "0",
      "name": "kworker/u8:1",
      "pid": "10673",
      "status": "Idle",
      "username": "root"
    },
    {
      "cpu_percent": "0.0069744845741247915",
      "create_time": "1525591774000",
      "exe": "",
      "memory_percent": "0",
      "name": "kworker/3:2",
      "pid": "10703",
      "status": "Idle",
      "username": "root"
    },
    {
      "cpu_percent": "0.001860398419396657",
      "create_time": "1525591810000",
      "exe": "",
      "memory_percent": "0",
      "name": "kworker/1:0",
      "pid": "10724",
      "status": "Idle",
      "username": "root"
    },
    {
      "cpu_percent": "0.018063608204162914",
      "create_time": "1525591960000",
      "exe": "",
      "memory_percent": "0",
      "name": "kworker/u8:0",
      "pid": "10813",
      "status": "Idle",
      "username": "root"
    },
    {
      "cpu_percent": "0.005161027462128852",
      "create_time": "1525591960000",
      "exe": "",
      "memory_percent": "0",
      "name": "kworker/0:2",
      "pid": "10814",
      "status": "Idle",
      "username": "root"
    },
    {
      "cpu_percent": "0",
      "create_time": "1525591960000",
      "exe": "",
      "memory_percent": "0",
      "name": "kworker/2:2",
      "pid": "10815",
      "status": "Idle",
      "username": "root"
    },
    {
      "cpu_percent": "0.03780430537695461",
      "create_time": "1525592083000",
      "exe": "",
      "memory_percent": "0",
      "name": "kworker/3:0",
      "pid": "10857",
      "status": "Idle",
      "username": "root"
    },
    {
      "cpu_percent": "0",
      "create_time": "1525592111000",
      "exe": "",
      "memory_percent": "0",
      "name": "kworker/1:2",
      "pid": "10872",
      "status": "Idle",
      "username": "root"
    },
    {
      "cpu_percent": "0",
      "create_time": "1525592262000",
      "exe": "",
      "memory_percent": "0",
      "name": "kworker/0:1",
      "pid": "10943",
      "status": "Idle",
      "username": "root"
    },
    {
      "cpu_percent": "0",
      "create_time": "1525592266000",
      "exe": "",
      "memory_percent": "0",
      "name": "kworker/2:1",
      "pid": "10944",
      "status": "Idle",
      "username": "root"
    },
    {
      "cpu_percent": "0.2293506574015553",
      "create_time": "1525592317000",
      "exe": "/home/zhang/Documents/Code/Go/src/github.com/SBOrg666/lite-yun-RESTful/main",
      "memory_percent": "0.19133493",
      "name": "main",
      "pid": "11059",
      "status": "Sleep",
      "username": "zhang"
    }
  ]
}